{
  "diagram_id": "ASD_VSD_PDA",
  "image_width": 606,
  "image_height": 500,
  "auto_configured": true,
  "locations": {
    "SVC": {
      "side": "right",
      "annotation_type": "saturation",
      "sat_x": 86,
      "sat_y": 170
    },
    "IVC": {
      "side": "right",
      "annotation_type": "saturation",
      "sat_x": 77,
      "sat_y": 416
    },
    "RA": {
      "side": "right",
      "annotation_type": "saturation_and_pressure",
      "sat_x": 116,
      "sat_y": 281,
      "pressure_x": 154,
      "pressure_y": 326
    },
    "RV": {
      "side": "right",
      "annotation_type": "saturation_and_pressure",
      "sat_x": 240,
      "sat_y": 370,
      "pressure_x": 288,
      "pressure_y": 389
    },
    "MPA": {
      "side": "right",
      "annotation_type": "saturation_and_pressure",
      "sat_x": 223,
      "sat_y": 251,
      "pressure_x": 225,
      "pressure_y": 221
    },
    "RPA": {
      "side": "right",
      "annotation_type": "saturation_and_pressure",
      "sat_x": 118,
      "sat_y": 113,
      "pressure_x": 28,
      "pressure_y": 115
    },
    "LPA": {
      "side": "right",
      "annotation_type": "saturation_and_pressure",
      "sat_x": 304,
      "sat_y": 134,
      "pressure_x": 366,
      "pressure_y": 137
    },
    "RPCWP": {
      "side": "left",
      "annotation_type": "pcwp",
      "pressure_x": 25,
      "pressure_y": 177
    },
    "LPCWP": {
      "side": "left",
      "annotation_type": "pcwp",
      "pressure_x": 434,
      "pressure_y": 191
    },
    "LA": {
      "side": "left",
      "annotation_type": "saturation_and_pressure",
      "sat_x": 280,
      "sat_y": 207,
      "pressure_x": 320,
      "pressure_y": 246
    },
    "LV": {
      "side": "left",
      "annotation_type": "saturation_and_pressure",
      "sat_x": 327,
      "sat_y": 325,
      "pressure_x": 379,
      "pressure_y": 352
    },
    "Descending_Aorta": {
      "side": "left",
      "annotation_type": "saturation_and_pressure",
      "sat_x": 272,
      "sat_y": 457,
      "pressure_x": 328,
      "pressure_y": 461
    },
    "RUPV": {
      "side": "left",
      "annotation_type": "saturation_and_pressure",
      "sat_x": 119,
      "sat_y": 175,
      "pressure_x": 40,
      "pressure_y": 150
    },
    "LUPV": {
      "side": "left",
      "annotation_type": "saturation_and_pressure",
      "sat_x": 347,
      "sat_y": 191,
      "pressure_x": 393,
      "pressure_y": 179
    },
    "RLPV": {
      "side": "left",
      "annotation_type": "saturation_and_pressure",
      "sat_x": 116,
      "sat_y": 208,
      "pressure_x": 37,
      "pressure_y": 201
    },
    "LLPV": {
      "side": "left",
      "annotation_type": "saturation_and_pressure",
      "sat_x": 370,
      "sat_y": 226,
      "pressure_x": 411,
      "pressure_y": 221
    }
  }
}