{
  "diagram_id": "CoarctationAorta_PDA",
  "image_width": 629,
  "image_height": 501,
  "auto_configured": true,
  "locations": {
    "SVC": {
      "side": "right",
      "annotation_type": "saturation",
      "sat_x": 137,
      "sat_y": 203
    },
    "IVC": {
      "side": "right",
      "annotation_type": "saturation",
      "sat_x": 136,
      "sat_y": 432
    },
    "RA": {
      "side": "right",
      "annotation_type": "saturation_and_pressure",
      "sat_x": 176,
      "sat_y": 292,
      "pressure_x": 210,
      "pressure_y": 330
    },
    "RV": {
      "side": "right",
      "annotation_type": "saturation_and_pressure",
      "sat_x": 295,
      "sat_y": 349,
      "pressure_x": 345,
      "pressure_y": 392
    },
    "MPA": {
      "side": "right",
      "annotation_type": "saturation_and_pressure",
      "sat_x": 271,
      "sat_y": 257,
      "pressure_x": 271,
      "pressure_y": 224
    },
    "RPA": {
      "side": "right",
      "annotation_type": "saturation_and_pressure",
      "sat_x": 165,
      "sat_y": 125,
      "pressure_x": 80,
      "pressure_y": 126
    },
    "LPA": {
      "side": "right",
      "annotation_type": "saturation_and_pressure",
      "sat_x": 340,
      "sat_y": 136,
      "pressure_x": 413,
      "pressure_y": 135
    },
    "RPCWP": {
      "side": "left",
      "annotation_type": "pcwp",
      "pressure_x": 48,
      "pressure_y": 186
    },
    "LPCWP": {
      "side": "left",
      "annotation_type": "pcwp",
      "pressure_x": 490,
      "pressure_y": 191
    },
    "LA": {
      "side": "left",
      "annotation_type": "saturation_and_pressure",
      "sat_x": 319,
      "sat_y": 216,
      "pressure_x": 361,
      "pressure_y": 246
    },
    "LV": {
      "side": "left",
      "annotation_type": "saturation_and_pressure",
      "sat_x": 380,
      "sat_y": 325,
      "pressure_x": 429,
      "pressure_y": 358
    },
    "Descending_Aorta": {
      "side": "left",
      "annotation_type": "saturation_and_pressure",
      "sat_x": 330,
      "sat_y": 454,
      "pressure_x": 385,
      "pressure_y": 461
    },
    "RUPV": {
      "side": "left",
      "annotation_type": "saturation_and_pressure",
      "sat_x": 166,
      "sat_y": 184,
      "pressure_x": 88,
      "pressure_y": 170
    },
    "LUPV": {
      "side": "left",
      "annotation_type": "saturation_and_pressure",
      "sat_x": 395,
      "sat_y": 191,
      "pressure_x": 443,
      "pressure_y": 181
    },
    "RLPV": {
      "side": "left",
      "annotation_type": "saturation_and_pressure",
      "sat_x": 168,
      "sat_y": 218,
      "pressure_x": 88,
      "pressure_y": 210
    },
    "LLPV": {
      "side": "left",
      "annotation_type": "saturation_and_pressure",
      "sat_x": 410,
      "sat_y": 226,
      "pressure_x": 455,
      "pressure_y": 219
    },
    "Ascending_aorta": {
      "side": "right",
      "annotation_type": "pressure_only",
      "custom": true,
      "pressure_x": 228,
      "pressure_y": 185
    }
  }
}