{
  "diagram_id": "Dextrocardia_TGA_IVS__S_D_D_",
  "image_width": 555,
  "image_height": 541,
  "auto_configured": true,
  "locations": {
    "SVC": {
      "side": "right",
      "annotation_type": "saturation",
      "sat_x": 161,
      "sat_y": 163
    },
    "IVC": {
      "side": "right",
      "annotation_type": "saturation",
      "sat_x": 166,
      "sat_y": 466
    },
    "RA": {
      "side": "right",
      "annotation_type": "saturation_and_pressure",
      "sat_x": 139,
      "sat_y": 244,
      "pressure_x": 187,
      "pressure_y": 243
    },
    "RV": {
      "side": "right",
      "annotation_type": "saturation_and_pressure",
      "sat_x": 123,
      "sat_y": 323,
      "pressure_x": 109,
      "pressure_y": 373
    },
    "MPA": {
      "side": "right",
      "annotation_type": "saturation_and_pressure",
      "sat_x": 277,
      "sat_y": 247,
      "pressure_x": 263,
      "pressure_y": 276
    },
    "RPA": {
      "side": "right",
      "annotation_type": "saturation_and_pressure",
      "sat_x": 200,
      "sat_y": 130,
      "pressure_x": 100,
      "pressure_y": 138
    },
    "LPA": {
      "side": "right",
      "annotation_type": "saturation_and_pressure",
      "sat_x": 377,
      "sat_y": 144,
      "pressure_x": 453,
      "pressure_y": 136
    },
    "RPCWP": {
      "side": "left",
      "annotation_type": "pcwp",
      "pressure_x": 59,
      "pressure_y": 237
    },
    "LPCWP": {
      "side": "left",
      "annotation_type": "pcwp",
      "pressure_x": 502,
      "pressure_y": 296
    },
    "LA": {
      "side": "left",
      "annotation_type": "saturation_and_pressure",
      "sat_x": 322,
      "sat_y": 270,
      "pressure_x": 339,
      "pressure_y": 315
    },
    "LV": {
      "side": "left",
      "annotation_type": "saturation_and_pressure",
      "sat_x": 237,
      "sat_y": 347,
      "pressure_x": 228,
      "pressure_y": 394
    },
    "Descending_Aorta": {
      "side": "left",
      "annotation_type": "saturation_and_pressure",
      "sat_x": 372,
      "sat_y": 445,
      "pressure_x": 454,
      "pressure_y": 446
    },
    "RUPV": {
      "side": "left",
      "annotation_type": "saturation_and_pressure",
      "sat_x": 126,
      "sat_y": 227,
      "pressure_x": 88,
      "pressure_y": 221
    },
    "LUPV": {
      "side": "left",
      "annotation_type": "saturation_and_pressure",
      "sat_x": 423,
      "sat_y": 277,
      "pressure_x": 471,
      "pressure_y": 273
    },
    "RLPV": {
      "side": "left",
      "annotation_type": "saturation_and_pressure",
      "sat_x": 114,
      "sat_y": 253,
      "pressure_x": 83,
      "pressure_y": 255
    },
    "LLPV": {
      "side": "left",
      "annotation_type": "saturation_and_pressure",
      "sat_x": 421,
      "sat_y": 315,
      "pressure_x": 467,
      "pressure_y": 318
    },
    "Ascending_Aorta": {
      "side": "right",
      "annotation_type": "pressure_only",
      "custom": true,
      "pressure_x": 262,
      "pressure_y": 172
    }
  }
}